auto_file_organizer/__init__.py
auto_file_organizer/autoorganizer.py
auto_file_organizer/file_ignore.py
auto_file_organizer/main.py
auto_file_organizer/model.py
auto_file_organizer/type_map.py
auto_file_organizer/undo.py
auto_file_organizer-1.0.0.dist-info/entry_points.txt
auto_file_organizer-1.0.0.dist-info/METADATA
auto_file_organizer-1.0.0.dist-info/WHEEL
auto_file_organizer-1.0.0.dist-info/RECORD
