Metadata-Version: 2.3
Name: auto-file-organizer
Version: 1.0.0
Summary: A smart Python script to automatically organize files by type, date, and more with undo and ignore support.
License: MIT
Author: Yash Kassa
Requires-Python: >=3.8,<4.0
Classifier: License :: OSI Approved :: MIT License
Classifier: Programming Language :: Python :: 3
Classifier: Programming Language :: Python :: 3.8
Classifier: Programming Language :: Python :: 3.9
Classifier: Programming Language :: Python :: 3.10
Classifier: Programming Language :: Python :: 3.11
Classifier: Programming Language :: Python :: 3.12
Classifier: Programming Language :: Python :: 3.13
